leostream/__init__.py
leostream/center.py
leostream/gateway.py
leostream/policy.py
leostream/pool.py
leostream/poolassignment.py
leostream/restapi.py
leostream/webresource.py
leostream-1.0.4.dist-info/LICENSE
leostream-1.0.4.dist-info/METADATA
leostream-1.0.4.dist-info/WHEEL
leostream-1.0.4.dist-info/top_level.txt
leostream-1.0.4.dist-info/RECORD
