Metadata-Version: 2.1
Name: leostream
Version: 1.0.4
Summary: Leostream Python client
Author: Joost Evertse
Author-email: <joustie@gmail.com>
Keywords: python,leostream,rest,api,client
Classifier: Development Status :: 4 - Beta
Classifier: Intended Audience :: Developers
Classifier: Environment :: Console
Classifier: Programming Language :: Python :: 3
Classifier: Operating System :: OS Independent
License-File: LICENSE
